changepy/__init__.py
changepy/costs.py
changepy/pelt.py
changepy-0.4.0.dist-info/LICENSE
changepy-0.4.0.dist-info/METADATA
changepy-0.4.0.dist-info/WHEEL
changepy-0.4.0.dist-info/top_level.txt
changepy-0.4.0.dist-info/RECORD
